finesse_virgo/__init__.py
finesse_virgo/actions.py
finesse_virgo/utils.py
finesse_virgo/virgo.py
finesse_virgo/katscript/00_virgo_common_file.kat
finesse_virgo/katscript/01_additional_katscript.kat
finesse_virgo/katscript/__init__.py
finesse_virgo/katscript/legacy/__init__.py
finesse_virgo/katscript/legacy/virgo_common_file_f2.kat
finesse_virgo-1.0.9.dist-info/LICENSE.md
finesse_virgo-1.0.9.dist-info/METADATA
finesse_virgo-1.0.9.dist-info/WHEEL
finesse_virgo-1.0.9.dist-info/top_level.txt
finesse_virgo-1.0.9.dist-info/RECORD
