Metadata-Version: 2.1
Name: finesse-virgo
Version: 1.0.9
Summary: Tools for modelling Virgo in Finesse 3.0
Home-page: https://gitlab.com/ifosim/finesse/finesse-virgo
Author: Daniel Brown
Author-email: daniel.brown@ligo.org
Project-URL: Bug Tracker, https://gitlab.com/ifosim/finesse/finesse-virgo/issues
Classifier: Programming Language :: Python :: 3
Classifier: Operating System :: OS Independent
Classifier: Topic :: Scientific/Engineering :: Physics
Classifier: Intended Audience :: Science/Research
Classifier: Natural Language :: English
Classifier: License :: OSI Approved :: GNU General Public License v3 or later (GPLv3+)
Requires-Python: >=3.8
License-File: LICENSE.md
Requires-Dist: finesse >=3.0a23.dev17
Requires-Dist: numpy
Requires-Dist: scipy
Requires-Dist: matplotlib
Requires-Dist: control
Requires-Dist: tqdm
Provides-Extra: docs
Requires-Dist: sphinx ; extra == 'docs'
Requires-Dist: sphinx-rtd-theme ; extra == 'docs'
Requires-Dist: sphinxcontrib-bibtex ; extra == 'docs'
Requires-Dist: sphinxcontrib-katex ; extra == 'docs'
Requires-Dist: sphinxcontrib-svg2pdfconverter ; extra == 'docs'
Requires-Dist: sphinxcontrib-programoutput ; extra == 'docs'
Requires-Dist: jupyter-sphinx ; extra == 'docs'
Requires-Dist: numpydoc ; extra == 'docs'
Requires-Dist: reslate ; extra == 'docs'
